jamdocs/__init__.py
jamdocs/bin/jamdocs
jamdocs/docs/ichigojam.zip
jamdocs-1.1.1.data/scripts/jamdocs
jamdocs-1.1.1.dist-info/DESCRIPTION.rst
jamdocs-1.1.1.dist-info/METADATA
jamdocs-1.1.1.dist-info/RECORD
jamdocs-1.1.1.dist-info/WHEEL
jamdocs-1.1.1.dist-info/metadata.json
jamdocs-1.1.1.dist-info/top_level.txt
