Metadata-Version: 2.0
Name: jamdocs
Version: 1.1.1
Summary: IchigoJam Docs
Home-page: https://github.com/BlueCocoa/jam
Author: Cocoa Oikawa
Author-email: cocoaoikawa@meowtain.edu.pl
License: MIT
Keywords: ichigojam docs
Platform: UNKNOWN
Classifier: Development Status :: 5 - Production/Stable
Classifier: License :: OSI Approved :: MIT License
Classifier: Programming Language :: Basic
